Flask_CacheOBJ-0.2.2.dist-info/DESCRIPTION.rst
Flask_CacheOBJ-0.2.2.dist-info/METADATA
Flask_CacheOBJ-0.2.2.dist-info/RECORD
Flask_CacheOBJ-0.2.2.dist-info/WHEEL
Flask_CacheOBJ-0.2.2.dist-info/metadata.json
Flask_CacheOBJ-0.2.2.dist-info/top_level.txt
flask_cacheobj/__init__.py
flask_cacheobj/_compat.py
flask_cacheobj/api.py
flask_cacheobj/cache.py
flask_cacheobj/consts.py
flask_cacheobj/format.py
flask_cacheobj/msgpackable.py
flask_cacheobj/proxy.py
flask_cacheobj/redis_client.py
flask_cacheobj/utils.py
