Metadata-Version: 2.0
Name: Flask-CacheOBJ
Version: 0.2.2
Summary: Flask-CacheOBJ provides some caching decorators
Home-page: https://github.com/liwushuo/Flask-CacheOBJ
Author: Ju Lin
Author-email: soasme@gmail.com
License: MIT
Platform: any
Classifier: Framework :: Flask
Classifier: Natural Language :: English
Classifier: Environment :: Web Environment
Classifier: Intended Audience :: Developers
Classifier: License :: OSI Approved :: MIT License
Classifier: Operating System :: OS Independent
Classifier: Programming Language :: Python
Classifier: Topic :: Internet :: WWW/HTTP :: Dynamic Content
Classifier: Topic :: Software Development :: Libraries :: Python Modules
Requires-Dist: Flask
Requires-Dist: decorator
Requires-Dist: msgpack-python
Requires-Dist: python-dateutil
Requires-Dist: pytz
Requires-Dist: redis
